.codeclimate.yml
.coveragerc
.gitignore
.travis.yml
LICENSE.md
README.rst
setup.py
test_requirements.txt
cannabis_reports/__init__.py
cannabis_reports/auth_proxy.py
cannabis_reports/base_api.py
cannabis_reports/base_model.py
cannabis_reports/exceptions.py
cannabis_reports.egg-info/PKG-INFO
cannabis_reports.egg-info/SOURCES.txt
cannabis_reports.egg-info/dependency_links.txt
cannabis_reports.egg-info/requires.txt
cannabis_reports.egg-info/top_level.txt
cannabis_reports/apis/__init__.py
cannabis_reports/apis/abstract_entity_endpoint.py
cannabis_reports/apis/abstract_item_endpoint.py
cannabis_reports/apis/abstract_product_endpoint.py
cannabis_reports/apis/dispensaries.py
cannabis_reports/apis/edibles.py
cannabis_reports/apis/extracts.py
cannabis_reports/apis/flowers.py
cannabis_reports/apis/producers.py
cannabis_reports/apis/products.py
cannabis_reports/apis/strains.py
cannabis_reports/models/__init__.py
cannabis_reports/models/abstract_item.py
cannabis_reports/models/address.py
cannabis_reports/models/dispensary.py
cannabis_reports/models/edible.py
cannabis_reports/models/effects_flavors.py
cannabis_reports/models/extract.py
cannabis_reports/models/flower.py
cannabis_reports/models/menu_item.py
cannabis_reports/models/producer.py
cannabis_reports/models/product.py
cannabis_reports/models/review.py
cannabis_reports/models/seed_company.py
cannabis_reports/models/strain.py
cannabis_reports/models/user.py
cannabis_reports/request_paginator/__init__.py
cannabis_reports/tests/__init__.py
cannabis_reports/tests/api_common.py
cannabis_reports/tests/api_entity.py
cannabis_reports/tests/api_product.py
cannabis_reports/tests/test_apis_dispensaries.py
cannabis_reports/tests/test_apis_edibles.py
cannabis_reports/tests/test_apis_extracts.py
cannabis_reports/tests/test_apis_flowers.py
cannabis_reports/tests/test_apis_producer.py
cannabis_reports/tests/test_apis_products.py
cannabis_reports/tests/test_apis_strains.py
cannabis_reports/tests/test_base_api.py
cannabis_reports/tests/test_base_model.py
cannabis_reports/tests/test_cannabis_reports.py
cannabis_reports/tests/test_exceptions.py
cannabis_reports/tests/test_request_paginator.py
